Metadata-Version: 2.1
Name: aspect-based-sentiment-analysis
Version: 2.0.3
Summary: Aspect Based Sentiment Analysis: Transformer & Interpretability (TensorFlow)
Home-page: https://github.com/ScalaConsultants/Aspect-Based-Sentiment-Analysis
Author: Rafal Rolczynski
Author-email: rafal.rolczynski@gmail.com
License: Apache-2.0
Platform: UNKNOWN
Requires-Python: ==3.7.*
Requires-Dist: tensorflow (==2.5)
Requires-Dist: transformers (==4.8)
Requires-Dist: pytest
Requires-Dist: scikit-learn
Requires-Dist: ipython
Requires-Dist: google-cloud-storage
Requires-Dist: testfixtures
Requires-Dist: optuna
Requires-Dist: spacy
